{
  "deposit": "Arriba",
  "withdrawal": "Próximo",
  "settle": "Liquidación de mano",
  "shop_consume": "Consumo en centros comerciales",
  "shop_income": "Adquisición de centro comercial",
  "buy_private_table_limit": "Comprar límite de mesa privada",
  "add_trial_coins": "Reposición de monedas de experiencia",
  "first_buy_bouns": "Regalo de primera compra",
  "issue_gold_clones": "Dar monedas de oro a los clones",
  "take_out_gold_form_clones": "Extracción de monedas de clones",
  "single_wallet_buy": "Retirar dinero de la cartera única",
  "single_wallet_return": "Devolver dinero a la cartera única",
  "ev_cashout_income": "Beneficios del seguro para vehículos eléctricos",
  "win_ev_cashout": "Tarjeta ganadora (ingresos por seguro de vehículos eléctricos)",
  "buy_time_bank": "Comprar banco de tiempo",
  "buy_time_bank_refund": "Reembolso del banco de tiempo de compra",
  "open_private_room": "Abrir una sala privada",
  "commission": "Participación del propietario",
  "withdrawal_by_master": "Retiro del propietario",
  "isir_add_coin": "Reposición de monedas robóticas",
  "gm_adjust": "Ajuste del gerente",
  "cms_add_deposit": "Aumentar el margen en segundo plano",
  "ante": "Nota anterior",
  "small_blinds": "Ciega pequeña",
  "big_blinds": "Ciega grande",
  "check": "Controlar",
  "bet": "Apuesta",
  "call": "Llamar",
  "raise": "Aumentar",
  "fold": "Doblar",
  "all_in": "Todo incluido",
  "coin_refund": "Retorno de monedas",
  "split_request": "Solicitud de división",
  "split_approval": "¿Estás de acuerdo con la división?",
  "buy_ev": "Comprar EV",
  "current_pot_amount": "Monto actual del pozo de premios",
  "force_bet_1bb": "Apuesta forzada 1BB"
}